konda/__init__.py
konda/__main__.py
konda/commands.py
konda/install.py
konda-0.1.0.dist-info/licenses/LICENSE
konda-0.1.0.dist-info/METADATA
konda-0.1.0.dist-info/WHEEL
konda-0.1.0.dist-info/entry_points.txt
konda-0.1.0.dist-info/top_level.txt
konda-0.1.0.dist-info/RECORD
