Metadata-Version: 2.4
Name: konda
Version: 0.1.0
Summary: A wrapper for conda commands with automatic Miniconda installation
Home-page: https://github.com/tamnguyenvan/konda
Author: Tam Nguyen
Author-email: tamnvhustcc@gmail.com
Classifier: Programming Language :: Python :: 3
Classifier: License :: OSI Approved :: MIT License
Classifier: Operating System :: OS Independent
Requires-Python: >=3.6
License-File: LICENSE
Dynamic: author
Dynamic: author-email
Dynamic: classifier
Dynamic: description
Dynamic: description-content-type
Dynamic: home-page
Dynamic: license-file
Dynamic: requires-python
Dynamic: summary
